yaml_dir_parser/__init__.py
yaml_dir_parser/data.py
yaml_dir_parser/data__test.py
ibots_yaml_dir_parser-0.0.1.dist-info/METADATA
ibots_yaml_dir_parser-0.0.1.dist-info/WHEEL
ibots_yaml_dir_parser-0.0.1.dist-info/top_level.txt
ibots_yaml_dir_parser-0.0.1.dist-info/RECORD
