Metadata-Version: 2.1
Name: ibots-yaml-dir-parser
Version: 0.0.1
Summary: Parses a directory of yaml and markdown data into a single Python dictionary.
Author-email: "Nicholas A. Del Grosso" <delgrosso.nick@gmail.com>
Requires-Python: >=3.11
Requires-Dist: markdown2
Requires-Dist: PyYAML
Provides-Extra: dev
Requires-Dist: pytest ; extra == 'dev'
Requires-Dist: ipdb ; extra == 'dev'
Provides-Extra: release
Requires-Dist: build ; extra == 'release'
Requires-Dist: twine ; extra == 'release'
